MANIFEST.in
README.md
setup.py
ioapi/__init__.py
ioapi/schema.json
ioapi.egg-info/PKG-INFO
ioapi.egg-info/SOURCES.txt
ioapi.egg-info/dependency_links.txt
ioapi.egg-info/requires.txt
ioapi.egg-info/top_level.txt