Metadata-Version: 2.1
Name: ioapi
Version: 0.0.12
Summary: A Python client for accessing the IOExplorer API
Home-page: UNKNOWN
Author: Ryan Marren
Author-email: rymarr@tuta.io
License: MIT
Platform: UNKNOWN
